PyRastrWin/__init__.py
PyRastrWin/rastr_win.py
PyRastrWin/calculations/__init__.py
PyRastrWin/calculations/calc_I_dop.py
PyRastrWin/calculations/dynamic.py
PyRastrWin/calculations/equivalent.py
PyRastrWin/calculations/mdp.py
PyRastrWin/calculations/regim.py
PyRastrWin/file_io/__init__.py
PyRastrWin/file_io/directories.py
PyRastrWin/file_io/load.py
PyRastrWin/file_io/save.py
PyRastrWin/loggers_config/__init__.py
PyRastrWin/loggers_config/loggers.py
PyRastrWin/settings/__init__.py
PyRastrWin/settings/alt_unit.py
PyRastrWin/settings/dynamic.py
PyRastrWin/settings/equivalents.py
PyRastrWin/settings/regime.py
PyRastrWin/tables/__init__.py
PyRastrWin/tables/node.py
tests/__init__.py
tests/test_pyrastrwin.py
PyRastrWin-0.1.6.dist-info/LICENSE
PyRastrWin-0.1.6.dist-info/METADATA
PyRastrWin-0.1.6.dist-info/WHEEL
PyRastrWin-0.1.6.dist-info/entry_points.txt
PyRastrWin-0.1.6.dist-info/top_level.txt
PyRastrWin-0.1.6.dist-info/RECORD
